Asic.v
module vc_Mux2
#(
  parameter p_nbits = 1
)(
  input      [p_nbits-1:0] in0, in1,
  input                    sel,
  output reg [p_nbits-1:0] out
);

  always @(*)
  begin
    case ( sel )
      1'd0 : out = in0;
      1'd1 : out = in1;
      default : out = {p_nbits{1'bx}};
    endcase
  end

endmodule


module vc_EnResetAsyncReg
#(
  parameter p_nbits       = 1,
  parameter p_reset_value = 0
)(
  input  logic               clk,   // Clock input
  input  logic               reset, // Sync reset input
  output logic [p_nbits-1:0] q,     // Data output
  input  logic [p_nbits-1:0] d,     // Data input
  input  logic               en     // Enable input
);

  always @(posedge clk or posedge reset) begin
    if (reset) begin
         q <= p_reset_value;
    end else if (en) begin
        q <= d;
      end
   end

endmodule


module Asic 
#(
  parameter p_divN_bits = 1,
  parameter p_divM_bits = 3
)(
  input  logic reset,
  input  logic clk,
  input  logic en_divN,

  input  logic [p_divN_bits-1:0] divN, // 0 for ÷4 and 1 for ÷8
  input  logic [p_divM_bits-1:0] divM, // 0 for ÷1, 1 for ÷2, \u2026, 7 for ÷8

  output logic clk_prescale_o,
  output logic clk_gate_o
);
  // divide-by-N (N = 4 or 8)
  logic div2q, div2d; 
  logic div4q, div4d;
  logic div8q, div8d;
  // logic en_divN;
  logic clkN; // 0 for ÷1, 1 for ÷2, \u2026, 7 for ÷8

  logic phase_pass;
  logic [p_divM_bits-1:0] counterM; // M
  logic clkM;

  // gating logic
  logic phase_gate;
  assign div2d   = ~div2q; // flop output fed back to flop input
  vc_EnResetAsyncReg div2 ( .clk(clk),.reset(reset),.q(div2q),.d(div2d),.en(en_divN) ); 
  assign div4d   = ~div4q;
  vc_EnResetAsyncReg div4 ( .clk(div2q),.reset(reset),.q(div4q),.d(div4d),.en(en_divN) ); 
  assign div8d   = ~div8q;
  vc_EnResetAsyncReg div8 ( .clk(div4q),.reset(reset),.q(div8q),.d(div8d),.en(en_divN) );

  vc_Mux2 muxN ( .in0(div4q),.in1(div8q),.sel(divN),.out(clkN) );

  always @(posedge clkN or posedge reset) begin
        if (reset) begin
            counterM   <= 0;    // like this for counterM, but rather just
            phase_pass <= 0;    // a reset in a posedge always block then
  	end else if (counterM >= divM) begin
  		counterM   <= 0;
  	        phase_pass <= 1;
  	    end else begin
  		counterM   <= counterM + 1;
  		phase_pass <= 0;
            end  	
  end

  always @(*)
    if (~clkN)
       phase_gate <= phase_pass;
       assign clkM = clkN & phase_gate;  

       assign clk_prescale_o = clkN;
       assign clk_gate_o     = clkM;

endmodule

Asic_tb.v
`timescale 1ps/1ps
`include "Asic.v"

module Asic_tb;
  localparam p_divN_bits = 1;
  localparam p_divM_bits = 3;

  reg reset, clk, en_divN;
  reg [p_divN_bits-1:0] divN;
  reg [p_divM_bits-1:0] divM;

  wire clk_prescale_o, clk_gate_o;

  Asic #(
    .p_divN_bits(p_divN_bits),
    .p_divM_bits(p_divM_bits)
  ) DUT (
    .reset(reset),
    .clk(clk),
    .en_divN(en_divN),
    .divN(divN),
    .divM(divM),
    .clk_prescale_o(clk_prescale_o),
    .clk_gate_o(clk_gate_o)
  );

always begin
 #5 clk = ~clk;
end

  initial begin 
    $dumpfile("Asic.vcd");
    $dumpvars;   
    
    reset = 1;
    clk = 0;
    en_divN = 0;
    divN = 0;
    divM = 0;

    #10 reset = 0;
    #10 en_divN=1;
  end

  initial begin
    #50  divN = 1;
    #300 divN = 0;
    #50  divM = 4;

    #400 $finish;
  end

endmodule

Asic.vcd
$date
	Tue Dec 19 13:24:32 2023
$end
$version
	Icarus Verilog
$end
$timescale
	1ps
$end
$scope module Asic_tb $end
$var wire 1 ! clk_prescale_o $end
$var wire 1 " clk_gate_o $end
$var reg 1 # clk $end
$var reg 3 $ divM [2:0] $end
$var reg 1 % divN $end
$var reg 1 & en_divN $end
$var reg 1 ' reset $end
$scope module DUT $end
$var wire 1 # clk $end
$var wire 1 ( clkM $end
$var wire 1 " clk_gate_o $end
$var wire 1 ! clk_prescale_o $end
$var wire 1 ) div2d $end
$var wire 1 * div4d $end
$var wire 1 + div8d $end
$var wire 3 , divM [2:0] $end
$var wire 1 % divN $end
$var wire 1 & en_divN $end
$var wire 1 ' reset $end
$var wire 1 - div8q $end
$var wire 1 . div4q $end
$var wire 1 / div2q $end
$var wire 1 0 clkN $end
$var reg 3 1 counterM [2:0] $end
$var reg 1 2 phase_gate $end
$var reg 1 3 phase_pass $end
$scope module div2 $end
$var wire 1 # clk $end
$var wire 1 ) d $end
$var wire 1 & en $end
$var wire 1 ' reset $end
$var reg 1 / q $end
$upscope $end
$scope module div4 $end
$var wire 1 / clk $end
$var wire 1 * d $end
$var wire 1 & en $end
$var wire 1 ' reset $end
$var reg 1 . q $end
$upscope $end
$scope module div8 $end
$var wire 1 . clk $end
$var wire 1 + d $end
$var wire 1 & en $end
$var wire 1 ' reset $end
$var reg 1 - q $end
$upscope $end
$scope module muxN $end
$var wire 1 . in0 $end
$var wire 1 - in1 $end
$var wire 1 % sel $end
$var reg 1 0 out $end
$upscope $end
$upscope $end
$upscope $end
$enddefinitions $end
#0
$dumpvars
03
02
b0 1
00
0/
0.
0-
b0 ,
1+
1*
1)
0(
1'
0&
0%
b0 $
0#
0"
0!
$end
#5
1#
#10
0#
0'
#15
1#
#20
0#
1&
#25
0+
13
1-
1!
10
0*
1.
0)
1/
1#
#30
0#
#35
1)
0/
1#
#40
0#
#45
12
0!
00
1*
0.
0)
1/
1#
#50
1"
1(
1!
10
0#
1%
#55
1)
0/
1#
#60
0#
#65
0"
0(
0!
00
1+
0-
0*
1.
0)
1/
1#
#70
0#
#75
1)
0/
1#
#80
0#
#85
1*
0.
0)
1/
1#
#90
0#
#95
1)
0/
1#
#100
0#
#105
1"
1(
1!
10
0+
1-
0*
1.
0)
1/
1#
#110
0#
#115
1)
0/
1#
#120
0#
#125
1*
0.
0)
1/
1#
#130
0#
#135
1)
0/
1#
#140
0#
#145
0"
0(
0!
00
1+
0-
0*
1.
0)
1/
1#
#150
0#
#155
1)
0/
1#
#160
0#
#165
1*
0.
0)
1/
1#
#170
0#
#175
1)
0/
1#
#180
0#
#185
1"
1(
1!
10
0+
1-
0*
1.
0)
1/
1#
#190
0#
#195
1)
0/
1#
#200
0#
#205
1*
0.
0)
1/
1#
#210
0#
#215
1)
0/
1#
#220
0#
#225
0"
0(
0!
00
1+
0-
0*
1.
0)
1/
1#
#230
0#
#235
1)
0/
1#
#240
0#
#245
1*
0.
0)
1/
1#
#250
0#
#255
1)
0/
1#
#260
0#
#265
1"
1(
1!
10
0+
1-
0*
1.
0)
1/
1#
#270
0#
#275
1)
0/
1#
#280
0#
#285
1*
0.
0)
1/
1#
#290
0#
#295
1)
0/
1#
#300
0#
#305
0"
0(
0!
00
1+
0-
0*
1.
0)
1/
1#
#310
0#
#315
1)
0/
1#
#320
0#
#325
1*
0.
0)
1/
1#
#330
0#
#335
1)
0/
1#
#340
0#
#345
1"
1(
1!
10
0+
1-
0*
1.
0)
1/
1#
#350
0#
0%
#355
1)
0/
1#
#360
0#
#365
0"
0(
0!
00
1*
0.
0)
1/
1#
#370
0#
#375
1)
0/
1#
#380
0#
#385
1+
0-
1"
1(
1!
10
0*
1.
0)
1/
1#
#390
0#
#395
1)
0/
1#
#400
0#
b100 $
b100 ,
#405
0"
0(
0!
00
1*
0.
0)
1/
1#
#410
0#
#415
1)
0/
1#
#420
0#
#425
0+
03
b1 1
1-
1"
1(
1!
10
0*
1.
0)
1/
1#
#430
0#
#435
1)
0/
1#
#440
0#
#445
02
0"
0(
0!
00
1*
0.
0)
1/
1#
#450
0#
#455
1)
0/
1#
#460
0#
#465
1+
b10 1
0-
1!
10
0*
1.
0)
1/
1#
#470
0#
#475
1)
0/
1#
#480
0#
#485
0!
00
1*
0.
0)
1/
1#
#490
0#
#495
1)
0/
1#
#500
0#
#505
0+
b11 1
1-
1!
10
0*
1.
0)
1/
1#
#510
0#
#515
1)
0/
1#
#520
0#
#525
0!
00
1*
0.
0)
1/
1#
#530
0#
#535
1)
0/
1#
#540
0#
#545
1+
b100 1
0-
1!
10
0*
1.
0)
1/
1#
#550
0#
#555
1)
0/
1#
#560
0#
#565
0!
00
1*
0.
0)
1/
1#
#570
0#
#575
1)
0/
1#
#580
0#
#585
0+
13
b0 1
1-
1!
10
0*
1.
0)
1/
1#
#590
0#
#595
1)
0/
1#
#600
0#
#605
12
0!
00
1*
0.
0)
1/
1#
#610
0#
#615
1)
0/
1#
#620
0#
#625
1+
03
b1 1
0-
1"
1(
1!
10
0*
1.
0)
1/
1#
#630
0#
#635
1)
0/
1#
#640
0#
#645
02
0"
0(
0!
00
1*
0.
0)
1/
1#
#650
0#
#655
1)
0/
1#
#660
0#
#665
0+
b10 1
1-
1!
10
0*
1.
0)
1/
1#
#670
0#
#675
1)
0/
1#
#680
0#
#685
0!
00
1*
0.
0)
1/
1#
#690
0#
#695
1)
0/
1#
#700
0#
#705
1+
b11 1
0-
1!
10
0*
1.
0)
1/
1#
#710
0#
#715
1)
0/
1#
#720
0#
#725
0!
00
1*
0.
0)
1/
1#
#730
0#
#735
1)
0/
1#
#740
0#
#745
0+
b100 1
1-
1!
10
0*
1.
0)
1/
1#
#750
0#
#755
1)
0/
1#
#760
0#
#765
0!
00
1*
0.
0)
1/
1#
#770
0#
#775
1)
0/
1#
#780
0#
#785
1+
13
b0 1
0-
1!
10
0*
1.
0)
1/
1#
#790
0#
#795
1)
0/
1#
